tradeflow/enums.py
tradeflow/libtradeflow.so
tradeflow/time_series.py
tradeflow/config.py
tradeflow/exceptions.py
tradeflow/__init__.py
tradeflow/ar_model.py
tradeflow/common/shared_libraries_registry.py
tradeflow/common/general_utils.py
tradeflow/common/config.py
tradeflow/common/exceptions.py
tradeflow/common/ctypes_utils.py
tradeflow/common/singleton.py
tradeflow/common/__init__.py
tradeflow/common/logger_utils.py
tradeflow.libs/libgcc_s-7393e603.so.1
tradeflow.libs/libstdc++-1b614e01.so.6.0.32
tradeflow-1.1.0.dist-info/WHEEL
tradeflow-1.1.0.dist-info/METADATA
tradeflow-1.1.0.dist-info/top_level.txt
tradeflow-1.1.0.dist-info/LICENSE
tradeflow-1.1.0.dist-info/RECORD
