Metadata-Version: 2.1
Name: tradeflow
Version: 1.1.0
Summary: A package to simulate autocorrelated time series of signs
Author-email: Martin Gangand <martin.gangand@gmail.com>
Project-URL: Homepage, https://martingangand.github.io/tradeflow/
Classifier: Programming Language :: Python :: 3
Classifier: Programming Language :: Python :: 3.8
Classifier: Programming Language :: Python :: 3.9
Classifier: Programming Language :: Python :: 3.10
Classifier: Programming Language :: Python :: 3.11
Classifier: Programming Language :: Python :: 3.12
Classifier: License :: OSI Approved :: MIT License
Classifier: Operating System :: OS Independent
Requires-Python: <3.13,>=3.8
License-File: LICENSE
Requires-Dist: matplotlib >=3.0.0
Requires-Dist: numpy >=1.21.0
Requires-Dist: pandas >=1.3.0
Requires-Dist: statsmodels >=0.12.2
Requires-Dist: scipy >=1.9.0
